dumpit/__init__.py
dumpit/coloring.py
dumpit/description.py
dumpit/export.py
dumpit/indent.py
dumpit/view.py
dumpit-0.6.0.dist-info/LICENSE
dumpit-0.6.0.dist-info/METADATA
dumpit-0.6.0.dist-info/WHEEL
dumpit-0.6.0.dist-info/top_level.txt
dumpit-0.6.0.dist-info/RECORD
